4bit_alu.v
module alu_4bit (
    input  [3:0] A,
    input  [3:0] B,
    input  [2:0] SEL,
    output reg [3:0] Y
);

always @(*) begin
    case (SEL)

        3'b000: Y = A + B;   // Addition
        3'b001: Y = A - B;   // Subtraction
        3'b010: Y = A & B;   // AND
        3'b011: Y = A | B;   // OR
        3'b100: Y = A ^ B;   // XOR
        3'b101: Y = ~A;      // NOT A
        3'b110: Y = A << 1;  // Left Shift
        3'b111: Y = A >> 1;  // Right Shift

        default: Y = 4'b0000;

    endcase
end

endmodule

4bit_alu_tb.v
`timescale 1ns / 1ps

module alu_4bit_tb;

reg  [3:0] A;
reg  [3:0] B;
reg  [2:0] SEL;
wire [3:0] Y;

alu_4bit uut (
    .A(A),
    .B(B),
    .SEL(SEL),
    .Y(Y)
);

initial begin
    $dumpfile("dump.vcd");
    $dumpvars(0, alu_4bit_tb);
end

initial begin

    A = 4'b0101;
    B = 4'b0011;

    SEL = 3'b000; #10;
    SEL = 3'b001; #10;
    SEL = 3'b010; #10;
    SEL = 3'b011; #10;
    SEL = 3'b100; #10;
    SEL = 3'b101; #10;
    SEL = 3'b110; #10;
    SEL = 3'b111; #10;

    $finish;
end

initial begin
    $monitor("Time=%0t A=%b B=%b SEL=%b Y=%b",
              $time, A, B, SEL, Y);
end

endmodule

dump.vcd
$date
	Sun May 17 21:16:39 2026
$end
$version
	Icarus Verilog
$end
$timescale
	1ps
$end
$scope module alu_4bit_tb $end
$var wire 4 ! Y [3:0] $end
$var reg 4 " A [3:0] $end
$var reg 4 # B [3:0] $end
$var reg 3 $ SEL [2:0] $end
$scope module uut $end
$var wire 4 % A [3:0] $end
$var wire 4 & B [3:0] $end
$var wire 3 ' SEL [2:0] $end
$var reg 4 ( Y [3:0] $end
$upscope $end
$upscope $end
$enddefinitions $end
$comment Show the parameter values. $end
$dumpall
$end
#0
$dumpvars
b1000 (
b0 '
b11 &
b101 %
b0 $
b11 #
b101 "
b1000 !
$end
#10000
b10 !
b10 (
b1 $
b1 '
#20000
b1 !
b1 (
b10 $
b10 '
#30000
b111 !
b111 (
b11 $
b11 '
#40000
b110 !
b110 (
b100 $
b100 '
#50000
b1010 !
b1010 (
b101 $
b101 '
#60000
b110 $
b110 '
#70000
b10 !
b10 (
b111 $
b111 '
